django_geo_entities/__init__.py
django_geo_entities/admin.py
django_geo_entities/apps.py
django_geo_entities/management/commands/update_geo_data.py
django_geo_entities/migrations/0001_initial.py
django_geo_entities/migrations/0002_alter_geocity_options_alter_geostate_options.py
django_geo_entities/migrations/__init__.py
django_geo_entities/models.py
django_geo_entities/tests.py
django_geo_entities/views.py
django_geo_entities-0.1.2.dist-info/LICENSE
django_geo_entities-0.1.2.dist-info/METADATA
django_geo_entities-0.1.2.dist-info/WHEEL
django_geo_entities-0.1.2.dist-info/RECORD
