Metadata-Version: 2.1
Name: django-geo-entities
Version: 0.1.2
Summary: Simple Django Models for Geo Entities
Home-page: https://github.com/devwaseem/django-geo-entities
License: MIT
Keywords: django,geo
Author: Waseem Akram
Author-email: waseem07799@gmail.com
Requires-Python: >=3.9
Classifier: Framework :: Django :: 3.0
Classifier: Framework :: Django :: 4
Classifier: Framework :: Django :: 4.0
Classifier: Framework :: Django :: 4.1
Classifier: Framework :: Django :: 4.2
Classifier: Framework :: Django :: 5.0
Classifier: License :: OSI Approved :: MIT License
Classifier: Programming Language :: Python :: 3
Classifier: Programming Language :: Python :: 3.9
Classifier: Programming Language :: Python :: 3.10
Classifier: Programming Language :: Python :: 3.11
Classifier: Programming Language :: Python :: 3.12
Requires-Dist: Django (>=3.2)
Requires-Dist: django-rich (>=1.9.0,<2.0.0)
Project-URL: Repository, https://github.com/devwaseem/django-geo-entities
